{
  "id": "1391837205319778367",
  "name": "nether-portal",
  "code": "NP",
  "description": "Nether portal-based obsidian farms",
  "currentCodeId": 2,
  "entries": [
    {
      "id": "1392006670233632778",
      "name": "The Obsidian Reactor",
      "code": "NP001",
      "timestamp": 1751954100741,
      "path": "NP001_The_Obsidian_Reactor"
    },
    {
      "id": "1392015750084038677",
      "name": "36k TNT Nether Portal Obsidian Farm",
      "code": "NP002",
      "timestamp": 1752052234749,
      "path": "NP002_36k_TNT_Nether_Portal_Obsidian_Farm"
    }
  ]
}